swirlc/__init__.py
swirlc/__main__.py
swirlc/log_handler.py
swirlc/main.py
swirlc/parser.py
swirlc/version.py
swirlc/antlr/SWIRLLexer.py
swirlc/antlr/SWIRLListener.py
swirlc/antlr/SWIRLParser.py
swirlc/antlr/SWIRLVisitor.py
swirlc/antlr/__init__.py
swirlc/compiler/__init__.py
swirlc/compiler/default.py
swirlc/config/__init__.py
swirlc/config/validator.py
swirlc/config/schemas/v1.0/config_schema.json
swirlc/core/__init__.py
swirlc/core/compiler.py
swirlc/core/entity.py
swirlc/core/translator.py
swirlc/core/utils.py
swirlc/translator/__init__.py
swirlc/translator/dax_translator.py
swirlc-0.0.1.dist-info/LICENSE
swirlc-0.0.1.dist-info/METADATA
swirlc-0.0.1.dist-info/WHEEL
swirlc-0.0.1.dist-info/entry_points.txt
swirlc-0.0.1.dist-info/top_level.txt
swirlc-0.0.1.dist-info/zip-safe
swirlc-0.0.1.dist-info/RECORD
