Metadata-Version: 2.1
Name: swirlc
Version: 0.0.1
Summary: Scientific Workflow Intermediate Representation Language
Author-email: Iacopo Colonnelli <iacopo.colonnelli@unito.it>, Doriana Medić <doriana.medic@unito.it>, Alberto Mulone <alberto.mulone@unito.it>
License: LGPL-3.0-or-later
Project-URL: Package, https://pypi.org/project/swirlc
Project-URL: Repository, https://github.com/alpha-unito/swirlc
Project-URL: Docker, https://hub.docker.com/r/alphaunito/swirlc
Classifier: Development Status :: 3 - Alpha
Classifier: License :: OSI Approved :: GNU Lesser General Public License v3 (LGPLv3)
Classifier: Intended Audience :: Developers
Classifier: Intended Audience :: Science/Research
Classifier: Operating System :: OS Independent
Classifier: Programming Language :: Python
Classifier: Programming Language :: Python :: 3 :: Only
Classifier: Programming Language :: Python :: 3.8
Classifier: Programming Language :: Python :: 3.9
Classifier: Programming Language :: Python :: 3.10
Classifier: Programming Language :: Python :: 3.11
Classifier: Topic :: Scientific/Engineering
Classifier: Topic :: System :: Distributed Computing
Requires-Python: >=3.8
License-File: LICENSE
Requires-Dist: antlr4-python3-runtime ==4.13.1
Requires-Dist: black ==24.4.2
Requires-Dist: importlib-resources ==6.4.0
Requires-Dist: jsonschema ==4.22.0
Requires-Dist: referencing ==0.35.1
Requires-Dist: ruamel.yaml ==0.18.6
Provides-Extra: bandit
Requires-Dist: bandit ==1.7.9 ; extra == 'bandit'
Provides-Extra: lint
Requires-Dist: codespell ==2.3.0 ; extra == 'lint'
Requires-Dist: flake8-bugbear ==24.4.26 ; extra == 'lint'
Requires-Dist: pyupgrade ==3.16.0 ; extra == 'lint'
Provides-Extra: test
Requires-Dist: pytest ==8.2.2 ; extra == 'test'
Requires-Dist: pytest-cov ==5.0.0 ; extra == 'test'
Requires-Dist: pytest-xdist ==3.6.1 ; extra == 'test'
